AUTHORS
LICENSE
MANIFEST.in
README.rst
setup.py
src/restible_flask/__init__.py
src/restible_flask/endpoint.py
src/restible_flask.egg-info/PKG-INFO
src/restible_flask.egg-info/SOURCES.txt
src/restible_flask.egg-info/dependency_links.txt
src/restible_flask.egg-info/requires.txt
src/restible_flask.egg-info/top_level.txt