Metadata-Version: 1.1
Name: restible-flask
Version: 0.2.2
Summary: Flask integration for restible library
Home-page: http://github.com/novopl/restible-flask
Author: Mateusz 'novo' Klos
Author-email: novopl@gmail.com
License: MIT
Keywords: restible REST restapi rest server flask
Platform: UNKNOWN
Classifier: Development Status :: 4 - Beta
Classifier: Topic :: Utilities
Classifier: Intended Audience :: Developers
Classifier: Programming Language :: Python
Classifier: License :: OSI Approved :: MIT License
